easylangchain/__init__.py
easylangchain/agents/__init__.py
easylangchain/agents/agent.py
easylangchain/examples/tryit.py
easylangchain/llms/__init__.py
easylangchain/llms/models.py
easylangchain/memorys/__init__.py
easylangchain/memorys/memory.py
easylangchain/messages/__init__.py
easylangchain/tools/__init__.py
easylangchain/utils/__init__.py
easylangchain/utils/check_version.py
easylangchain/utils/logger.py
easylangchain-0.2.3.dist-info/LICENSE
easylangchain-0.2.3.dist-info/METADATA
easylangchain-0.2.3.dist-info/WHEEL
easylangchain-0.2.3.dist-info/top_level.txt
easylangchain-0.2.3.dist-info/RECORD
