Metadata-Version: 2.1
Name: easylangchain
Version: 0.2.3
Summary: A simplified wrapper around LangChain for easy tool usage.
Author-email: zengzhiyi <1694609389@qq.com>
Project-URL: homepage, https://github.com/zhiyiZeng/easylangchain
Requires-Python: >=3.10
License-File: LICENSE
Requires-Dist: langchain
Requires-Dist: langchain-core
Requires-Dist: langchain-community
Requires-Dist: langchain-openai
